PySide2-stubs/Qt3DAnimation.pyi
PySide2-stubs/Qt3DCore.pyi
PySide2-stubs/Qt3DExtras.pyi
PySide2-stubs/Qt3DInput.pyi
PySide2-stubs/Qt3DLogic.pyi
PySide2-stubs/Qt3DRender.pyi
PySide2-stubs/QtAxContainer.pyi
PySide2-stubs/QtCharts.pyi
PySide2-stubs/QtConcurrent.pyi
PySide2-stubs/QtCore.pyi
PySide2-stubs/QtDataVisualization.pyi
PySide2-stubs/QtGui.pyi
PySide2-stubs/QtHelp.pyi
PySide2-stubs/QtLocation.pyi
PySide2-stubs/QtMacExtras.pyi
PySide2-stubs/QtMultimedia.pyi
PySide2-stubs/QtMultimediaWidgets.pyi
PySide2-stubs/QtNetwork.pyi
PySide2-stubs/QtOpenGL.pyi
PySide2-stubs/QtOpenGLFunctions.pyi
PySide2-stubs/QtPositioning.pyi
PySide2-stubs/QtPrintSupport.pyi
PySide2-stubs/QtQml.pyi
PySide2-stubs/QtQuick.pyi
PySide2-stubs/QtQuickControls2.pyi
PySide2-stubs/QtQuickWidgets.pyi
PySide2-stubs/QtRemoteObjects.pyi
PySide2-stubs/QtScript.pyi
PySide2-stubs/QtScriptTools.pyi
PySide2-stubs/QtScxml.pyi
PySide2-stubs/QtSensors.pyi
PySide2-stubs/QtSerialPort.pyi
PySide2-stubs/QtSql.pyi
PySide2-stubs/QtSvg.pyi
PySide2-stubs/QtTest.pyi
PySide2-stubs/QtTextToSpeech.pyi
PySide2-stubs/QtUiTools.pyi
PySide2-stubs/QtWebChannel.pyi
PySide2-stubs/QtWebEngine.pyi
PySide2-stubs/QtWebEngineCore.pyi
PySide2-stubs/QtWebEngineWidgets.pyi
PySide2-stubs/QtWebSockets.pyi
PySide2-stubs/QtWidgets.pyi
PySide2-stubs/QtWinExtras.pyi
PySide2-stubs/QtX11Extras.pyi
PySide2-stubs/QtXml.pyi
PySide2-stubs/QtXmlPatterns.pyi
PySide2-stubs/__init__.pyi
shiboken2-stubs/__init__.pyi
shiboken2-stubs/shiboken2.pyi
PySide2_stubs-5.15.2.1.2.dist-info/LICENSE
PySide2_stubs-5.15.2.1.2.dist-info/METADATA
PySide2_stubs-5.15.2.1.2.dist-info/WHEEL
PySide2_stubs-5.15.2.1.2.dist-info/top_level.txt
PySide2_stubs-5.15.2.1.2.dist-info/RECORD
