Metadata-Version: 2.1
Name: PySide2-stubs
Version: 5.15.2.1.2
Summary: PEP561 stub files for the *PySide2/Qt5 for Python* framework
Home-page: https://github.com/python-qt-tools/PySide2-stubs
Author: Philippe Fremy
Author-email: phil.fremy@free.fr
License: LGPL v2.1
Project-URL: Bug Tracker, https://github.com/bluebird75/pyside2-stubs/issues
Platform: UNKNOWN
Classifier: Development Status :: 5 - Production/Stable
Classifier: Programming Language :: Python :: 3
Classifier: License :: OSI Approved :: GNU Lesser General Public License v2 (LGPLv2)
Classifier: Operating System :: OS Independent
Classifier: Intended Audience :: Developers
Classifier: Typing :: Stubs Only
Requires-Python: >=3.6
License-File: LICENSE
Requires-Dist: mypy (>=0.940)
Requires-Dist: PySide2 (>=5.11.0)
Provides-Extra: dev
Requires-Dist: pytest ; extra == 'dev'
